{"keypoint_1": {"x": 416, "y": 92}, "keypoint_2": {"x": 424, "y": 78}, "keypoint_3": {"x": 429, "y": 78}, "keypoint_4": {"x": 433, "y": 77}, "keypoint_5": {"x": 406, "y": 78}, "keypoint_6": {"x": 399, "y": 78}, "keypoint_7": {"x": 394, "y": 78}, "keypoint_8": {"x": 442, "y": 82}, "keypoint_9": {"x": 385, "y": 84}, "keypoint_10": {"x": 428, "y": 109}, "keypoint_11": {"x": 407, "y": 110}, "keypoint_12": {"x": 488, "y": 167}, "keypoint_13": {"x": 340, "y": 171}, "keypoint_14": {"x": 512, "y": 276}, "keypoint_15": {"x": 322, "y": 282}, "keypoint_16": {"x": 435, "y": 198}, "keypoint_17": {"x": 399, "y": 199}, "keypoint_18": {"x": 427, "y": 167}, "keypoint_19": {"x": 412, "y": 167}, "keypoint_20": {"x": 426, "y": 160}, "keypoint_21": {"x": 408, "y": 160}, "keypoint_22": {"x": 428, "y": 170}, "keypoint_23": {"x": 405, "y": 170}, "keypoint_24": {"x": 462, "y": 374}, "keypoint_25": {"x": 361, "y": 371}, "keypoint_26": {"x": 606, "y": 439}, "keypoint_27": {"x": 227, "y": 435}, "keypoint_28": {"x": 623, "y": 602}, "keypoint_29": {"x": 208, "y": 602}, "keypoint_30": {"x": 610, "y": 626}, "keypoint_31": {"x": 220, "y": 625}, "keypoint_32": {"x": 685, "y": 645}, "keypoint_33": {"x": 150, "y": 643}}