{"keypoint_1": {"x": 352, "y": 123}, "keypoint_2": {"x": 346, "y": 114}, "keypoint_3": {"x": 345, "y": 113}, "keypoint_4": {"x": 344, "y": 113}, "keypoint_5": {"x": 345, "y": 115}, "keypoint_6": {"x": 344, "y": 115}, "keypoint_7": {"x": 342, "y": 115}, "keypoint_8": {"x": 330, "y": 119}, "keypoint_9": {"x": 329, "y": 121}, "keypoint_10": {"x": 349, "y": 133}, "keypoint_11": {"x": 347, "y": 134}, "keypoint_12": {"x": 325, "y": 176}, "keypoint_13": {"x": 319, "y": 173}, "keypoint_14": {"x": 339, "y": 233}, "keypoint_15": {"x": 397, "y": 169}, "keypoint_16": {"x": 347, "y": 279}, "keypoint_17": {"x": 464, "y": 144}, "keypoint_18": {"x": 344, "y": 290}, "keypoint_19": {"x": 481, "y": 145}, "keypoint_20": {"x": 345, "y": 287}, "keypoint_21": {"x": 482, "y": 142}, "keypoint_22": {"x": 347, "y": 284}, "keypoint_23": {"x": 476, "y": 142}, "keypoint_24": {"x": 315, "y": 311}, "keypoint_25": {"x": 283, "y": 315}, "keypoint_26": {"x": 407, "y": 299}, "keypoint_27": {"x": 198, "y": 365}, "keypoint_28": {"x": 403, "y": 392}, "keypoint_29": {"x": 120, "y": 406}, "keypoint_30": {"x": 392, "y": 410}, "keypoint_31": {"x": 104, "y": 408}, "keypoint_32": {"x": 456, "y": 405}, "keypoint_33": {"x": 127, "y": 432}}