{"keypoint_1": {"x": 530, "y": 176}, "keypoint_2": {"x": 546, "y": 158}, "keypoint_3": {"x": 554, "y": 159}, "keypoint_4": {"x": 560, "y": 160}, "keypoint_5": {"x": 521, "y": 155}, "keypoint_6": {"x": 512, "y": 155}, "keypoint_7": {"x": 504, "y": 156}, "keypoint_8": {"x": 570, "y": 168}, "keypoint_9": {"x": 494, "y": 162}, "keypoint_10": {"x": 542, "y": 198}, "keypoint_11": {"x": 514, "y": 194}, "keypoint_12": {"x": 616, "y": 279}, "keypoint_13": {"x": 434, "y": 264}, "keypoint_14": {"x": 625, "y": 411}, "keypoint_15": {"x": 406, "y": 384}, "keypoint_16": {"x": 577, "y": 454}, "keypoint_17": {"x": 433, "y": 420}, "keypoint_18": {"x": 564, "y": 474}, "keypoint_19": {"x": 439, "y": 439}, "keypoint_20": {"x": 555, "y": 456}, "keypoint_21": {"x": 446, "y": 421}, "keypoint_22": {"x": 554, "y": 449}, "keypoint_23": {"x": 448, "y": 416}, "keypoint_24": {"x": 565, "y": 486}, "keypoint_25": {"x": 462, "y": 478}, "keypoint_26": {"x": 704, "y": 564}, "keypoint_27": {"x": 367, "y": 534}, "keypoint_28": {"x": 712, "y": 674}, "keypoint_29": {"x": 307, "y": 674}, "keypoint_30": {"x": 698, "y": 692}, "keypoint_31": {"x": 312, "y": 698}, "keypoint_32": {"x": 761, "y": 734}, "keypoint_33": {"x": 255, "y": 715}}